ml_gates/__init__.py
ml_gates/text_reader.py
ml_gates/data/my_code.py
ml_gates-0.1.dist-info/METADATA
ml_gates-0.1.dist-info/WHEEL
ml_gates-0.1.dist-info/top_level.txt
ml_gates-0.1.dist-info/RECORD
