Metadata-Version: 2.1
Name: ml-gates
Version: 0.1
Summary: Code for AND, NOT, OR, NOR, NAND, XOR
Home-page: https://github.com/savioratharv/prac_testing
Author: davinci003
Author-email: freegpt00@gmail.com
